[{"id":1,"name":"Fred"},{"id":2,"name":"Daphne"},{"id":3,"name":"Velma"},{"id":4,"name":"Shaggy"},{"id":5,"name":"Scooby"},{"id":6,"name":"Fred"},{"id":7,"name":"Daphne"},{"id":8,"name":"Velma"},{"id":9,"name":"Shaggy"},{"id":10,"name":"Scooby"},{"id":11,"name":"Fred"},{"id":12,"name":"Daphne"},{"id":13,"name":"Velma"},{"id":14,"name":"Shaggy"},{"id":15,"name":"Scooby"},{"id":16,"name":"Fred"},{"id":17,"name":"Daphne"},{"id":18,"name":"Velma"},{"id":19,"name":"Shaggy"},{"id":20,"name":"Scooby"},{"id":21,"name":"Fred"},{"id":22,"name":"Daphne"},{"id":23,"name":"Velma"},{"id":24,"name":"Shaggy"},{"id":25,"name":"Scooby"},{"id":26,"name":"Fred"},{"id":27,"name":"Daphne"},{"id":28,"name":"Velma"},{"id":29,"name":"Shaggy"},{"id":30,"name":"Scooby"},{"id":31,"name":"Fred"},{"id":32,"name":"Daphne"},{"id":33,"name":"Velma"},{"id":34,"name":"Shaggy"},{"id":35,"name":"Scooby"},{"id":36,"name":"Fred"},{"id":37,"name":"Daphne"},{"id":38,"name":"Velma"},{"id":39,"name":"Shaggy"},{"id":40,"name":"Scooby"},{"id":41,"name":"Fred"},{"id":42,"name":"Daphne"},{"id":43,"name":"Velma"},{"id":44,"name":"Shaggy"},{"id":45,"name":"Scooby"},{"id":46,"name":"Fred"},{"id":47,"name":"Daphne"},{"id":48,"name":"Velma"},{"id":49,"name":"Shaggy"},{"id":50,"name":"Scooby"},{"id":51,"name":"Fred"},{"id":52,"name":"Daphne"},{"id":53,"name":"Velma"},{"id":54,"name":"Shaggy"},{"id":55,"name":"Scooby"},{"id":56,"name":"Fred"},{"id":57,"name":"Daphne"},{"id":58,"name":"Velma"},{"id":59,"name":"Shaggy"},{"id":60,"name":"Scooby"},{"id":61,"name":"Fred"},{"id":62,"name":"Daphne"},{"id":63,"name":"Velma"},{"id":64,"name":"Shaggy"},{"id":65,"name":"Scooby"},{"id":66,"name":"Fred"},{"id":67,"name":"Daphne"},{"id":68,"name":"Velma"},{"id":69,"name":"Shaggy"},{"id":70,"name":"Scooby"},{"id":71,"name":"Fred"},{"id":72,"name":"Daphne"},{"id":73,"name":"Velma"},{"id":74,"name":"Shaggy"},{"id":75,"name":"Scooby"},{"id":76,"name":"Fred"},{"id":77,"name":"Daphne"},{"id":78,"name":"Velma"},{"id":79,"name":"Shaggy"},{"id":80,"name":"Scooby"},{"id":81,"name":"Fred"},{"id":82,"name":"Daphne"},{"id":83,"name":"Velma"},{"id":84,"name":"Shaggy"},{"id":85,"name":"Scooby"},{"id":86,"name":"Fred"},{"id":87,"name":"Daphne"},{"id":88,"name":"Velma"},{"id":89,"name":"Shaggy"},{"id":90,"name":"Scooby"},{"id":91,"name":"Fred"},{"id":92,"name":"Daphne"},{"id":93,"name":"Velma"},{"id":94,"name":"Shaggy"},{"id":95,"name":"Scooby"},{"id":96,"name":"Fred"},{"id":97,"name":"Daphne"},{"id":98,"name":"Velma"},{"id":99,"name":"Shaggy"},{"id":100,"name":"Scooby"},{"id":101,"name":"Fred"},{"id":102,"name":"Daphne"},{"id":103,"name":"Velma"},{"id":104,"name":"Shaggy"},{"id":105,"name":"Scooby"},{"id":106,"name":"Fred"},{"id":107,"name":"Daphne"},{"id":108,"name":"Velma"},{"id":109,"name":"Shaggy"},{"id":110,"name":"Scooby"},{"id":111,"name":"Fred"},{"id":112,"name":"Daphne"},{"id":113,"name":"Velma"},{"id":114,"name":"Shaggy"},{"id":115,"name":"Scooby"},{"id":116,"name":"Fred"},{"id":117,"name":"Daphne"},{"id":118,"name":"Velma"},{"id":119,"name":"Shaggy"},{"id":120,"name":"Scooby"},{"id":121,"name":"Fred"},{"id":122,"name":"Daphne"},{"id":123,"name":"Velma"},{"id":124,"name":"Shaggy"},{"id":125,"name":"Scooby"},{"id":126,"name":"Fred"},{"id":127,"name":"Daphne"},{"id":128,"name":"Velma"},{"id":129,"name":"Shaggy"},{"id":130,"name":"Scooby"},{"id":131,"name":"Fred"},{"id":132,"name":"Daphne"},{"id":133,"name":"Velma"},{"id":134,"name":"Shaggy"},{"id":135,"name":"Scooby"},{"id":136,"name":"Fred"},{"id":137,"name":"Daphne"},{"id":138,"name":"Velma"},{"id":139,"name":"Shaggy"},{"id":140,"name":"Scooby"},{"id":141,"name":"Fred"},{"id":142,"name":"Daphne"},{"id":143,"name":"Velma"},{"id":144,"name":"Shaggy"},{"id":145,"name":"Scooby"},{"id":146,"name":"Fred"},{"id":147,"name":"Daphne"},{"id":148,"name":"Velma"},{"id":149,"name":"Shaggy"},{"id":150,"name":"Scooby"},{"id":151,"name":"Fred"},{"id":152,"name":"Daphne"},{"id":153,"name":"Velma"},{"id":154,"name":"Shaggy"},{"id":155,"name":"Scooby"},{"id":156,"name":"Fred"},{"id":157,"name":"Daphne"},{"id":158,"name":"Velma"},{"id":159,"name":"Shaggy"},{"id":160,"name":"Scooby"},{"id":161,"name":"Fred"},{"id":162,"name":"Daphne"},{"id":163,"name":"Velma"},{"id":164,"name":"Shaggy"},{"id":165,"name":"Scooby"},{"id":166,"name":"Fred"},{"id":167,"name":"Daphne"},{"id":168,"name":"Velma"},{"id":169,"name":"Shaggy"},{"id":170,"name":"Scooby"}]